<!-- This is optional and allows you to set password policy! -->
<valuePolicy xmlns="http://midpoint.evolveum.com/xml/ns/public/common/common-3" xmlns:c="http://midpoint.evolveum.com/xml/ns/public/common/common-3" xmlns:icfs="http://midpoint.evolveum.com/xml/ns/public/connector/icf-1/resource-schema-3" xmlns:org="http://midpoint.evolveum.com/xml/ns/public/common/org-3" xmlns:q="http://prism.evolveum.com/xml/ns/public/query-3" xmlns:ri="http://midpoint.evolveum.com/xml/ns/public/resource/instance-3" xmlns:t="http://prism.evolveum.com/xml/ns/public/types-3" oid="00000000-0000-1111-0000-000000000003">
    <name>Custom Password Policy</name>
    <description>Custom password policy</description>
    <stringPolicy>
        <description>Testing string policy</description>
        <limitations>
            <minLength>3</minLength>
        </limitations>
    </stringPolicy>
</valuePolicy>
